{
	"ImportPath": "github.com/hashrocket/ws",
	"GoVersion": "go1.7",
	"GodepVersion": "v74",
	"Deps": [
		{
			"ImportPath": "github.com/chzyer/readline",
			"Comment": "v1.4-4-g8159bd3",
			"Rev": "8159bd380cc4d5b344668c55e969b9d16165368d"
		},
		{
			"ImportPath": "github.com/inconshreveable/mousetrap",
			"Rev": "76626ae9c91c4f2a10f34cad8ce83ea42c93bb75"
		},
		{
			"ImportPath": "github.com/spf13/cobra",
			"Rev": "9c28e4bbd74e5c3ed7aacbc552b2cab7cfdfe744"
		},
		{
			"ImportPath": "github.com/spf13/pflag",
			"Rev": "103ce5cd2042f2fe629c1957abb64ab3e7f50235"
		},
		{
			"ImportPath": "golang.org/x/net/websocket",
			"Rev": "6250b412798208e6c90b03b7c4f226de5aa299e2"
		}
	]
}
